llms/__init__.py
llms/__main__.py
llms/db.py
llms/index.html
llms/llms.json
llms/main.py
llms/providers-extra.json
llms/providers.json
llms/extensions/analytics/ui/index.mjs
llms/extensions/app/README.md
llms/extensions/app/__init__.py
llms/extensions/app/db.py
llms/extensions/app/ui/Recents.mjs
llms/extensions/app/ui/index.mjs
llms/extensions/app/ui/threadStore.mjs
llms/extensions/computer/README.md
llms/extensions/computer/__init__.py
llms/extensions/computer/base.py
llms/extensions/computer/bash.py
llms/extensions/computer/computer.py
llms/extensions/computer/edit.py
llms/extensions/computer/filesystem.py
llms/extensions/computer/platform.py
llms/extensions/computer/run.py
llms/extensions/core_tools/CALCULATOR.md
llms/extensions/core_tools/__init__.py
llms/extensions/core_tools/ui/index.mjs
llms/extensions/core_tools/ui/codemirror/codemirror.css
llms/extensions/core_tools/ui/codemirror/codemirror.js
llms/extensions/core_tools/ui/codemirror/addon/edit/closebrackets.js
llms/extensions/core_tools/ui/codemirror/addon/edit/closetag.js
llms/extensions/core_tools/ui/codemirror/addon/edit/continuelist.js
llms/extensions/core_tools/ui/codemirror/addon/edit/matchbrackets.js
llms/extensions/core_tools/ui/codemirror/addon/edit/matchtags.js
llms/extensions/core_tools/ui/codemirror/addon/edit/trailingspace.js
llms/extensions/core_tools/ui/codemirror/addon/selection/active-line.js
llms/extensions/core_tools/ui/codemirror/addon/selection/mark-selection.js
llms/extensions/core_tools/ui/codemirror/addon/selection/selection-pointer.js
llms/extensions/core_tools/ui/codemirror/doc/docs.css
llms/extensions/core_tools/ui/codemirror/doc/source_sans.woff
llms/extensions/core_tools/ui/codemirror/mode/clike/clike.js
llms/extensions/core_tools/ui/codemirror/mode/javascript/index.html
llms/extensions/core_tools/ui/codemirror/mode/javascript/javascript.js
llms/extensions/core_tools/ui/codemirror/mode/javascript/typescript.html
llms/extensions/core_tools/ui/codemirror/mode/python/python.js
llms_py-3.0.25.dist-info/licenses/LICENSE
llms_py-3.0.25.dist-info/METADATA
llms_py-3.0.25.dist-info/WHEEL
llms_py-3.0.25.dist-info/entry_points.txt
llms_py-3.0.25.dist-info/top_level.txt
llms_py-3.0.25.dist-info/RECORD
